pyalgostrategypool/__init__.py
pyalgostrategypool/aroon_crossover.py
pyalgostrategypool/aroon_crossover_bracket.py
pyalgostrategypool/aroon_crossover_cover.py
pyalgostrategypool/bollinger_bands.py
pyalgostrategypool/bollinger_bands_bracket.py
pyalgostrategypool/bollinger_bands_cover.py
pyalgostrategypool/ema_crossover.py
pyalgostrategypool/ema_crossover_bracket.py
pyalgostrategypool/ema_heikin_ashi_crossover.py
pyalgostrategypool/macd_crossover.py
pyalgostrategypool/macd_crossover_bracket.py
pyalgostrategypool/open_range_breakout_crossover.py
pyalgostrategypool/open_range_breakout_crossover_bracket.py
pyalgostrategypool/open_range_breakout_crossover_cover.py
pyalgostrategypool/reverse_rsi_crossover.py
pyalgostrategypool/reverse_rsi_crossover_bracket.py
pyalgostrategypool/reverse_rsi_crossover_cover.py
pyalgostrategypool/sma_crossover.py
pyalgostrategypool/sma_crossover_bracket.py
pyalgostrategypool/sma_heikin_ashi_crossover.py
pyalgostrategypool/stochastic_crossover.py
pyalgostrategypool/stochastic_crossover_bracket.py
pyalgostrategypool/stochastic_crossover_cover.py
pyalgostrategypool/strategy_aroon_crossover_bracket_order.py
pyalgostrategypool/strategy_aroon_crossover_cover_order.py
pyalgostrategypool/strategy_bollinger_bands_bracket_order.py
pyalgostrategypool/strategy_bollinger_bands_cover_order.py
pyalgostrategypool/strategy_ema_bracket_order.py
pyalgostrategypool/strategy_ema_regular_order.py
pyalgostrategypool/strategy_inverse_ema_scalping_regular_order.py
pyalgostrategypool/strategy_macd_bracket_order.py
pyalgostrategypool/strategy_macd_regular_order.py
pyalgostrategypool/strategy_open_range_breakout_bracket_order.py
pyalgostrategypool/strategy_open_range_breakout_cover_order.py
pyalgostrategypool/strategy_reverse_rsi_bracket_order.py
pyalgostrategypool/strategy_reverse_rsi_cover_order.py
pyalgostrategypool/strategy_sma_bracket_order.py
pyalgostrategypool/strategy_sma_regular_order.py
pyalgostrategypool/strategy_stochastic_crossover_bracket_order.py
pyalgostrategypool-2022.9.3.dist-info/LICENSE
pyalgostrategypool-2022.9.3.dist-info/METADATA
pyalgostrategypool-2022.9.3.dist-info/WHEEL
pyalgostrategypool-2022.9.3.dist-info/top_level.txt
pyalgostrategypool-2022.9.3.dist-info/RECORD
