Metadata-Version: 2.1
Name: pyalgostrategypool
Version: 2022.9.3
Summary: Official pool of Algorithmic Trading Strategies for the AlgoBulls Platform
Home-page: https://github.com/algobulls/pyalgostrategypool
Author: Pushpak Dagade
Author-email: pushpak@algobulls.com
License: UNKNOWN
Project-URL: Source, https://github.com/algobulls/pyalgostrategypool
Project-URL: Documentation, https://pyalgostrategypool.readthedocs.io/en/latest/
Project-URL: Bug Reports, https://github.com/algobulls/pyalgostrategypool/issues
Project-URL: Say Thanks!, https://saythanks.io/to/guanidene%40gmail.com
Keywords: algotrading algorithmictrading trading strategies algostrategies apis
Platform: UNKNOWN
Classifier: Development Status :: 3 - Alpha
Classifier: Intended Audience :: Developers
Classifier: Intended Audience :: Financial and Insurance Industry
Classifier: Topic :: Software Development :: Libraries
Classifier: Topic :: Office/Business :: Financial
Classifier: Topic :: Software Development :: Libraries :: Python Modules
Classifier: License :: OSI Approved :: MIT License
Classifier: Programming Language :: Python :: 3
Classifier: Programming Language :: Python :: 3.6
Classifier: Programming Language :: Python :: 3.7
Classifier: Programming Language :: Python :: 3.8
Requires-Python: >=3.6
Requires-Dist: pyalgotrading (>=2021.1.1)
Requires-Dist: TA-Lib (>=0.4.17)
